broadworks_ocip_soap/__init__.py
broadworks_ocip_soap/api.py
broadworks_ocip_soap-0.4.0.dist-info/METADATA
broadworks_ocip_soap-0.4.0.dist-info/WHEEL
broadworks_ocip_soap-0.4.0.dist-info/top_level.txt
broadworks_ocip_soap-0.4.0.dist-info/RECORD
