Metadata-Version: 2.4
Name: broadworks-ocip-soap
Version: 0.4.0
Summary: API interface to the OCI-P SOAP provisioning interface of a Broadworks softswitch.
Author-email: Jordan Prescott <hello@minimalmind.io>
License: MIT License
Keywords: broadworks,oci,soap,telephony,voip,cisco
Classifier: Intended Audience :: Developers
Classifier: License :: OSI Approved :: MIT License
Classifier: Programming Language :: Python
Classifier: Programming Language :: Python :: 3
Classifier: Programming Language :: Python :: 3.9
Classifier: Programming Language :: Python :: 3.10
Classifier: Programming Language :: Python :: 3.12
Classifier: Operating System :: OS Independent
Classifier: Topic :: Software Development :: Libraries
Classifier: Topic :: Utilities
Requires-Python: <3.13,>=3.9
Requires-Dist: attr>=0.3.2
Requires-Dist: broadworks-ocip>=2.2.0
Requires-Dist: requests>=2.32.3
Requires-Dist: zeep>=4.3.1
